fastapi_async_sql_profiler/__init__.py
fastapi_async_sql_profiler/config.py
fastapi_async_sql_profiler/crud.py
fastapi_async_sql_profiler/custom_types.py
fastapi_async_sql_profiler/database.py
fastapi_async_sql_profiler/dependencies.py
fastapi_async_sql_profiler/favicon.ico
fastapi_async_sql_profiler/main.py
fastapi_async_sql_profiler/models.py
fastapi_async_sql_profiler/pages.py
fastapi_async_sql_profiler/repository.py
fastapi_async_sql_profiler/routers.py
fastapi_async_sql_profiler/schemas/common_schemas.py
fastapi_async_sql_profiler/schemas/query_info_schema.py
fastapi_async_sql_profiler/schemas/request_info_schema.py
fastapi_async_sql_profiler/schemas/response_info_schema.py
fastapi_async_sql_profiler/services.py
fastapi_async_sql_profiler/sql_middleware.py
fastapi_async_sql_profiler/start_debugger.py
fastapi_async_sql_profiler/templates/base.html
fastapi_async_sql_profiler/templates/highlight/local-css.html
fastapi_async_sql_profiler/templates/highlight/local-scripts.html
fastapi_async_sql_profiler/templates/highlight.min.js
fastapi_async_sql_profiler/templates/inclusion/clear_db_menu.html
fastapi_async_sql_profiler/templates/inclusion/pagination.html
fastapi_async_sql_profiler/templates/inclusion/query_list_menu.html
fastapi_async_sql_profiler/templates/inclusion/query_sql_detail_menu.html
fastapi_async_sql_profiler/templates/inclusion/request_detail_menu.html
fastapi_async_sql_profiler/templates/inclusion/request_summary_row.html
fastapi_async_sql_profiler/templates/inclusion/root_filter.html
fastapi_async_sql_profiler/templates/inclusion/root_menu.html
fastapi_async_sql_profiler/templates/page_clear_db.html
fastapi_async_sql_profiler/templates/query_sql_details.html
fastapi_async_sql_profiler/templates/request_detail.html
fastapi_async_sql_profiler/templates/request_show.html
fastapi_async_sql_profiler/templates/requests_sql.html
fastapi_async_sql_profiler/templates/response_clear_db.html
fastapi_async_sql_profiler/templates/scripts/js-scripts.html
fastapi_async_sql_profiler-0.1.4.1.dist-info/LICENSE
fastapi_async_sql_profiler-0.1.4.1.dist-info/METADATA
fastapi_async_sql_profiler-0.1.4.1.dist-info/WHEEL
fastapi_async_sql_profiler-0.1.4.1.dist-info/RECORD
