Metadata-Version: 2.1
Name: fastapi_async_sql_profiler
Version: 0.1.4.1
Summary: fastapi async sqlalchemy profiler
License: MIT
Author: itzero-ru
Author-email: paw100d@gmail.com
Requires-Python: >=3.10
Classifier: License :: OSI Approved :: MIT License
Classifier: Programming Language :: Python :: 3
Classifier: Programming Language :: Python :: 3.10
Classifier: Programming Language :: Python :: 3.11
Classifier: Programming Language :: Python :: 3.12
Provides-Extra: pdf
Requires-Dist: asyncpg (>=0.30.0)
Requires-Dist: fastapi (>=0.115.0)
Requires-Dist: jinja2 (>=3.1.4)
Requires-Dist: psycopg2-binary (>=2.9.10)
Requires-Dist: python-dotenv (>=1.0.1)
Requires-Dist: sqlalchemy[asyncio] (>=2.0.16)
Requires-Dist: sqlparse (>=0.5.1)
Project-URL: Repository, https://github.com/itzero-ru/fastapi-async-sql-profiler
